{
  "version": "1",
  "node_id": "node0",
  "next_file_id": 11153,
  "snapshot_sequence_number": 449,
  "wal_file_sequence_number": 300297,
  "catalog_sequence_number": 62,
  "parquet_size_bytes": 129590,
  "row_count": 2269,
  "min_time": 1747408801271298527,
  "max_time": 1747409393249910531,
  "databases": [
    [
      4,
      {
        "tables": [
          [
            12,
            [
              {
                "id": 11128,
                "path": "node0/dbs/ControlCommands-4/update_waterTempSetpoint-12/2025-05-16/15-20/0000300297.parquet",
                "size_bytes": 3700,
                "row_count": 20,
                "chunk_time": 1747408800000000000,
                "min_time": 1747408828329550041,
                "max_time": 1747409383135653584
              }
            ]
          ],
          [
            1,
            [
              {
                "id": 11129,
                "path": "node0/dbs/ControlCommands-4/update_fanEnabled-1/2025-05-16/15-20/0000300297.parquet",
                "size_bytes": 4980,
                "row_count": 123,
                "chunk_time": 1747408800000000000,
                "min_time": 1747408802310786848,
                "max_time": 1747409392272310637
              }
            ]
          ],
          [
            5,
            [
              {
                "id": 11132,
                "path": "node0/dbs/ControlCommands-4/update_fanSpeed-5/2025-05-16/15-20/0000300297.parquet",
                "size_bytes": 5041,
                "row_count": 123,
                "chunk_time": 1747408800000000000,
                "min_time": 1747408802760073651,
                "max_time": 1747409392220947197
              }
            ]
          ],
          [
            7,
            [
              {
                "id": 11134,
                "path": "node0/dbs/ControlCommands-4/update_temperatureSetpoint-7/2025-05-16/15-20/0000300297.parquet",
                "size_bytes": 4675,
                "row_count": 123,
                "chunk_time": 1747408800000000000,
                "min_time": 1747408802879388721,
                "max_time": 1747409393185831812
              }
            ]
          ],
          [
            3,
            [
              {
                "id": 11136,
                "path": "node0/dbs/ControlCommands-4/update_heatingValvePosition-3/2025-05-16/15-20/0000300297.parquet",
                "size_bytes": 4703,
                "row_count": 123,
                "chunk_time": 1747408800000000000,
                "min_time": 1747408802667448059,
                "max_time": 1747409392329053864
              }
            ]
          ],
          [
            2,
            [
              {
                "id": 11138,
                "path": "node0/dbs/ControlCommands-4/update_unitEnable-2/2025-05-16/15-20/0000300297.parquet",
                "size_bytes": 5070,
                "row_count": 184,
                "chunk_time": 1747408800000000000,
                "min_time": 1747408802447810414,
                "max_time": 1747409393249910531
              }
            ]
          ],
          [
            10,
            [
              {
                "id": 11140,
                "path": "node0/dbs/ControlCommands-4/update_temperatureSource-10/2025-05-16/15-20/0000300297.parquet",
                "size_bytes": 3893,
                "row_count": 41,
                "chunk_time": 1747408800000000000,
                "min_time": 1747408808223712753,
                "max_time": 1747409390263316550
              }
            ]
          ],
          [
            8,
            [
              {
                "id": 11141,
                "path": "node0/dbs/ControlCommands-4/update_pumpRuntime-8/2025-05-16/15-20/0000300297.parquet",
                "size_bytes": 4414,
                "row_count": 41,
                "chunk_time": 1747408800000000000,
                "min_time": 1747408808133407105,
                "max_time": 1747409390149654900
              }
            ]
          ],
          [
            9,
            [
              {
                "id": 11142,
                "path": "node0/dbs/ControlCommands-4/update_isLead-9/2025-05-16/15-20/0000300297.parquet",
                "size_bytes": 3840,
                "row_count": 41,
                "chunk_time": 1747408800000000000,
                "min_time": 1747408808283506557,
                "max_time": 1747409390207923237
              }
            ]
          ],
          [
            11,
            [
              {
                "id": 11143,
                "path": "node0/dbs/ControlCommands-4/update_firingRate-11/2025-05-16/15-20/0000300297.parquet",
                "size_bytes": 4098,
                "row_count": 20,
                "chunk_time": 1747408800000000000,
                "min_time": 1747408828127221076,
                "max_time": 1747409383206880673
              }
            ]
          ],
          [
            4,
            [
              {
                "id": 11146,
                "path": "node0/dbs/ControlCommands-4/update_outdoorDamperPosition-4/2025-05-16/15-20/0000300297.parquet",
                "size_bytes": 5153,
                "row_count": 123,
                "chunk_time": 1747408800000000000,
                "min_time": 1747408802524828173,
                "max_time": 1747409392160946347
              }
            ]
          ],
          [
            6,
            [
              {
                "id": 11147,
                "path": "node0/dbs/ControlCommands-4/update_coolingValvePosition-6/2025-05-16/15-20/0000300297.parquet",
                "size_bytes": 4679,
                "row_count": 123,
                "chunk_time": 1747408800000000000,
                "min_time": 1747408802239686907,
                "max_time": 1747409392410837495
              }
            ]
          ]
        ]
      }
    ],
    [
      3,
      {
        "tables": [
          [
            9,
            [
              {
                "id": 11130,
                "path": "node0/dbs/Locations-3/update_isLead-9/2025-05-16/15-20/0000300297.parquet",
                "size_bytes": 3840,
                "row_count": 41,
                "chunk_time": 1747408800000000000,
                "min_time": 1747408807215347275,
                "max_time": 1747409389982478753
              }
            ]
          ],
          [
            6,
            [
              {
                "id": 11131,
                "path": "node0/dbs/Locations-3/update_temperatureSetpoint-6/2025-05-16/15-20/0000300297.parquet",
                "size_bytes": 4674,
                "row_count": 123,
                "chunk_time": 1747408800000000000,
                "min_time": 1747408801903405491,
                "max_time": 1747409392473818468
              }
            ]
          ],
          [
            12,
            [
              {
                "id": 11133,
                "path": "node0/dbs/Locations-3/update_firingRate-12/2025-05-16/15-20/0000300297.parquet",
                "size_bytes": 4098,
                "row_count": 20,
                "chunk_time": 1747408800000000000,
                "min_time": 1747408827068701506,
                "max_time": 1747409382110306179
              }
            ]
          ],
          [
            8,
            [
              {
                "id": 11135,
                "path": "node0/dbs/Locations-3/update_coolingValvePosition-8/2025-05-16/15-20/0000300297.parquet",
                "size_bytes": 4680,
                "row_count": 123,
                "chunk_time": 1747408800000000000,
                "min_time": 1747408801271298527,
                "max_time": 1747409391817179150
              }
            ]
          ],
          [
            7,
            [
              {
                "id": 11137,
                "path": "node0/dbs/Locations-3/update_unitEnable-7/2025-05-16/15-20/0000300297.parquet",
                "size_bytes": 5071,
                "row_count": 184,
                "chunk_time": 1747408800000000000,
                "min_time": 1747408802029080385,
                "max_time": 1747409392536091718
              }
            ]
          ],
          [
            0,
            [
              {
                "id": 11139,
                "path": "node0/dbs/Locations-3/metrics-0/2025-05-16/15-20/0000300297.parquet",
                "size_bytes": 21104,
                "row_count": 99,
                "chunk_time": 1747408800000000000,
                "min_time": 1747408813895314588,
                "max_time": 1747409377167850553
              }
            ]
          ],
          [
            4,
            [
              {
                "id": 11144,
                "path": "node0/dbs/Locations-3/update_outdoorDamperPosition-4/2025-05-16/15-20/0000300297.parquet",
                "size_bytes": 5149,
                "row_count": 123,
                "chunk_time": 1747408800000000000,
                "min_time": 1747408801721102870,
                "max_time": 1747409392043715189
              }
            ]
          ],
          [
            3,
            [
              {
                "id": 11145,
                "path": "node0/dbs/Locations-3/update_fanEnabled-3/2025-05-16/15-20/0000300297.parquet",
                "size_bytes": 4982,
                "row_count": 123,
                "chunk_time": 1747408800000000000,
                "min_time": 1747408801629106377,
                "max_time": 1747409391934252678
              }
            ]
          ],
          [
            13,
            [
              {
                "id": 11148,
                "path": "node0/dbs/Locations-3/update_waterTempSetpoint-13/2025-05-16/15-20/0000300297.parquet",
                "size_bytes": 3700,
                "row_count": 20,
                "chunk_time": 1747408800000000000,
                "min_time": 1747408827131679118,
                "max_time": 1747409382194929290
              }
            ]
          ],
          [
            5,
            [
              {
                "id": 11149,
                "path": "node0/dbs/Locations-3/update_fanSpeed-5/2025-05-16/15-20/0000300297.parquet",
                "size_bytes": 5044,
                "row_count": 123,
                "chunk_time": 1747408800000000000,
                "min_time": 1747408801555335846,
                "max_time": 1747409391987714331
              }
            ]
          ],
          [
            10,
            [
              {
                "id": 11150,
                "path": "node0/dbs/Locations-3/update_pumpRuntime-10/2025-05-16/15-20/0000300297.parquet",
                "size_bytes": 4414,
                "row_count": 41,
                "chunk_time": 1747408800000000000,
                "min_time": 1747408807302419954,
                "max_time": 1747409390036788776
              }
            ]
          ],
          [
            2,
            [
              {
                "id": 11151,
                "path": "node0/dbs/Locations-3/update_heatingValvePosition-2/2025-05-16/15-20/0000300297.parquet",
                "size_bytes": 4695,
                "row_count": 123,
                "chunk_time": 1747408800000000000,
                "min_time": 1747408801448937762,
                "max_time": 1747409391882666506
              }
            ]
          ],
          [
            11,
            [
              {
                "id": 11152,
                "path": "node0/dbs/Locations-3/update_temperatureSource-11/2025-05-16/15-20/0000300297.parquet",
                "size_bytes": 3893,
                "row_count": 41,
                "chunk_time": 1747408800000000000,
                "min_time": 1747408807135174687,
                "max_time": 1747409389929320329
              }
            ]
          ]
        ]
      }
    ]
  ]
}