{
  "version": "1",
  "node_id": "node0",
  "next_file_id": 4232,
  "snapshot_sequence_number": 289,
  "wal_file_sequence_number": 179546,
  "catalog_sequence_number": 52,
  "parquet_size_bytes": 130770,
  "row_count": 3720,
  "min_time": 1747234200610700832,
  "max_time": 1747234799368194066,
  "databases": [
    [
      4,
      {
        "tables": [
          [
            7,
            [
              {
                "id": 4207,
                "path": "node0/dbs/ControlCommands-4/update_temperatureSetpoint-7/2025-05-14/14-50/0000179546.parquet",
                "size_bytes": 5263,
                "row_count": 200,
                "chunk_time": 1747234200000000000,
                "min_time": 1747234204198976966,
                "max_time": 1747234797557472082
              }
            ]
          ],
          [
            9,
            [
              {
                "id": 4208,
                "path": "node0/dbs/ControlCommands-4/update_isLead-9/2025-05-14/14-50/0000179546.parquet",
                "size_bytes": 4169,
                "row_count": 80,
                "chunk_time": 1747234200000000000,
                "min_time": 1747234210336241542,
                "max_time": 1747234799268966140
              }
            ]
          ],
          [
            2,
            [
              {
                "id": 4210,
                "path": "node0/dbs/ControlCommands-4/update_unitEnable-2/2025-05-14/14-50/0000179546.parquet",
                "size_bytes": 6095,
                "row_count": 320,
                "chunk_time": 1747234200000000000,
                "min_time": 1747234201187397593,
                "max_time": 1747234798392700752
              }
            ]
          ],
          [
            8,
            [
              {
                "id": 4211,
                "path": "node0/dbs/ControlCommands-4/update_pumpRuntime-8/2025-05-14/14-50/0000179546.parquet",
                "size_bytes": 3992,
                "row_count": 80,
                "chunk_time": 1747234200000000000,
                "min_time": 1747234210412865114,
                "max_time": 1747234799170645175
              }
            ]
          ],
          [
            5,
            [
              {
                "id": 4212,
                "path": "node0/dbs/ControlCommands-4/update_fanSpeed-5/2025-05-14/14-50/0000179546.parquet",
                "size_bytes": 4677,
                "row_count": 200,
                "chunk_time": 1747234200000000000,
                "min_time": 1747234203853881805,
                "max_time": 1747234797634165431
              }
            ]
          ],
          [
            12,
            [
              {
                "id": 4213,
                "path": "node0/dbs/ControlCommands-4/update_waterTempSetpoint-12/2025-05-14/14-50/0000179546.parquet",
                "size_bytes": 3897,
                "row_count": 40,
                "chunk_time": 1747234200000000000,
                "min_time": 1747234201260007473,
                "max_time": 1747234786320530300
              }
            ]
          ],
          [
            6,
            [
              {
                "id": 4215,
                "path": "node0/dbs/ControlCommands-4/update_coolingValvePosition-6/2025-05-14/14-50/0000179546.parquet",
                "size_bytes": 5250,
                "row_count": 200,
                "chunk_time": 1747234200000000000,
                "min_time": 1747234202776799136,
                "max_time": 1747234796557873643
              }
            ]
          ],
          [
            1,
            [
              {
                "id": 4217,
                "path": "node0/dbs/ControlCommands-4/update_fanEnabled-1/2025-05-14/14-50/0000179546.parquet",
                "size_bytes": 4614,
                "row_count": 200,
                "chunk_time": 1747234200000000000,
                "min_time": 1747234204083123032,
                "max_time": 1747234797377296599
              }
            ]
          ],
          [
            4,
            [
              {
                "id": 4218,
                "path": "node0/dbs/ControlCommands-4/update_outdoorDamperPosition-4/2025-05-14/14-50/0000179546.parquet",
                "size_bytes": 4806,
                "row_count": 200,
                "chunk_time": 1747234200000000000,
                "min_time": 1747234203965622978,
                "max_time": 1747234797455391203
              }
            ]
          ],
          [
            11,
            [
              {
                "id": 4219,
                "path": "node0/dbs/ControlCommands-4/update_firingRate-11/2025-05-14/14-50/0000179546.parquet",
                "size_bytes": 3359,
                "row_count": 40,
                "chunk_time": 1747234200000000000,
                "min_time": 1747234201339208727,
                "max_time": 1747234786249872033
              }
            ]
          ],
          [
            3,
            [
              {
                "id": 4220,
                "path": "node0/dbs/ControlCommands-4/update_heatingValvePosition-3/2025-05-14/14-50/0000179546.parquet",
                "size_bytes": 5305,
                "row_count": 200,
                "chunk_time": 1747234200000000000,
                "min_time": 1747234203725133456,
                "max_time": 1747234796459661727
              }
            ]
          ],
          [
            10,
            [
              {
                "id": 4222,
                "path": "node0/dbs/ControlCommands-4/update_temperatureSource-10/2025-05-14/14-50/0000179546.parquet",
                "size_bytes": 4223,
                "row_count": 80,
                "chunk_time": 1747234200000000000,
                "min_time": 1747234210175769314,
                "max_time": 1747234799368194066
              }
            ]
          ]
        ]
      }
    ],
    [
      3,
      {
        "tables": [
          [
            12,
            [
              {
                "id": 4209,
                "path": "node0/dbs/Locations-3/update_firingRate-12/2025-05-14/14-50/0000179546.parquet",
                "size_bytes": 3359,
                "row_count": 40,
                "chunk_time": 1747234200000000000,
                "min_time": 1747234200610700832,
                "max_time": 1747234785667446073
              }
            ]
          ],
          [
            7,
            [
              {
                "id": 4214,
                "path": "node0/dbs/Locations-3/update_unitEnable-7/2025-05-14/14-50/0000179546.parquet",
                "size_bytes": 6087,
                "row_count": 320,
                "chunk_time": 1747234200000000000,
                "min_time": 1747234200809196913,
                "max_time": 1747234797982070216
              }
            ]
          ],
          [
            6,
            [
              {
                "id": 4216,
                "path": "node0/dbs/Locations-3/update_temperatureSetpoint-6/2025-05-14/14-50/0000179546.parquet",
                "size_bytes": 5265,
                "row_count": 200,
                "chunk_time": 1747234200000000000,
                "min_time": 1747234202323733096,
                "max_time": 1747234796347169496
              }
            ]
          ],
          [
            8,
            [
              {
                "id": 4221,
                "path": "node0/dbs/Locations-3/update_coolingValvePosition-8/2025-05-14/14-50/0000179546.parquet",
                "size_bytes": 5252,
                "row_count": 200,
                "chunk_time": 1747234200000000000,
                "min_time": 1747234201891807220,
                "max_time": 1747234795925987193
              }
            ]
          ],
          [
            4,
            [
              {
                "id": 4223,
                "path": "node0/dbs/Locations-3/update_outdoorDamperPosition-4/2025-05-14/14-50/0000179546.parquet",
                "size_bytes": 4804,
                "row_count": 200,
                "chunk_time": 1747234200000000000,
                "min_time": 1747234202462069274,
                "max_time": 1747234796269451087
              }
            ]
          ],
          [
            10,
            [
              {
                "id": 4224,
                "path": "node0/dbs/Locations-3/update_pumpRuntime-10/2025-05-14/14-50/0000179546.parquet",
                "size_bytes": 3993,
                "row_count": 80,
                "chunk_time": 1747234200000000000,
                "min_time": 1747234209351672284,
                "max_time": 1747234798274900126
              }
            ]
          ],
          [
            2,
            [
              {
                "id": 4225,
                "path": "node0/dbs/Locations-3/update_heatingValvePosition-2/2025-05-14/14-50/0000179546.parquet",
                "size_bytes": 5300,
                "row_count": 200,
                "chunk_time": 1747234200000000000,
                "min_time": 1747234202060392939,
                "max_time": 1747234796019259643
              }
            ]
          ],
          [
            9,
            [
              {
                "id": 4226,
                "path": "node0/dbs/Locations-3/update_isLead-9/2025-05-14/14-50/0000179546.parquet",
                "size_bytes": 4169,
                "row_count": 80,
                "chunk_time": 1747234200000000000,
                "min_time": 1747234209443540476,
                "max_time": 1747234798201281920
              }
            ]
          ],
          [
            13,
            [
              {
                "id": 4227,
                "path": "node0/dbs/Locations-3/update_waterTempSetpoint-13/2025-05-14/14-50/0000179546.parquet",
                "size_bytes": 3897,
                "row_count": 40,
                "chunk_time": 1747234200000000000,
                "min_time": 1747234200742589096,
                "max_time": 1747234785798015405
              }
            ]
          ],
          [
            3,
            [
              {
                "id": 4228,
                "path": "node0/dbs/Locations-3/update_fanEnabled-3/2025-05-14/14-50/0000179546.parquet",
                "size_bytes": 4607,
                "row_count": 200,
                "chunk_time": 1747234200000000000,
                "min_time": 1747234202194218139,
                "max_time": 1747234796104292080
              }
            ]
          ],
          [
            5,
            [
              {
                "id": 4229,
                "path": "node0/dbs/Locations-3/update_fanSpeed-5/2025-05-14/14-50/0000179546.parquet",
                "size_bytes": 4679,
                "row_count": 200,
                "chunk_time": 1747234200000000000,
                "min_time": 1747234202587003271,
                "max_time": 1747234796181440258
              }
            ]
          ],
          [
            11,
            [
              {
                "id": 4230,
                "path": "node0/dbs/Locations-3/update_temperatureSource-11/2025-05-14/14-50/0000179546.parquet",
                "size_bytes": 4225,
                "row_count": 80,
                "chunk_time": 1747234200000000000,
                "min_time": 1747234209255270300,
                "max_time": 1747234798109408140
              }
            ]
          ],
          [
            0,
            [
              {
                "id": 4231,
                "path": "node0/dbs/Locations-3/metrics-0/2025-05-14/14-50/0000179546.parquet",
                "size_bytes": 19483,
                "row_count": 40,
                "chunk_time": 1747234200000000000,
                "min_time": 1747234211938057826,
                "max_time": 1747234795111825117
              }
            ]
          ]
        ]
      }
    ]
  ]
}